pasco/__init__.py
pasco/character_library.py
pasco/code_node_device.py
pasco/control_node_device.py
pasco/datasheets.py
pasco/pasco_ble_device.py
pasco/pasco_bot.py
pasco-0.3.65.dist-info/LICENSE
pasco-0.3.65.dist-info/METADATA
pasco-0.3.65.dist-info/WHEEL
pasco-0.3.65.dist-info/top_level.txt
pasco-0.3.65.dist-info/RECORD
