Metadata-Version: 2.1
Name: pasco
Version: 0.3.65
Summary: PASCO Python API for Wireless Sensors
Author: Waqas Saeed
Project-URL: Bug Tracker, https://github.com/PASCOscientific/pasco_python/issues
Classifier: Programming Language :: Python :: 3.11
Classifier: License :: Other/Proprietary License
Classifier: Operating System :: Microsoft :: Windows
Classifier: Operating System :: MacOS
Classifier: Operating System :: Unix
Requires-Python: >=3.11
License-File: LICENSE
Requires-Dist: bleak==0.20.2
Requires-Dist: nest_asyncio==1.5.6
